{
  "topRGs": [
    {
      "cost": 413.6,
      "subscription": "sub-idf-01",
      "name": "rg-fabric-global"
    },
    {
      "cost": 404.36,
      "subscription": "sub-idf-01",
      "name": "rg-moussa-aboubakar"
    },
    {
      "cost": 208.44,
      "subscription": "sub-idf-01",
      "name": "rg-lydia-arezki"
    },
    {
      "cost": 174.39,
      "subscription": "sub-idf-01",
      "name": "rg-taoufik-mellah"
    },
    {
      "cost": 158.97,
      "subscription": "sub-idf-01",
      "name": "rg-marouan-boulahtouf"
    },
    {
      "cost": 154.58,
      "subscription": "sub-idf-01",
      "name": "rg-nicolas-bedikian"
    },
    {
      "cost": 152.02,
      "subscription": "sub-lyon-01",
      "name": "databricks_demo"
    },
    {
      "cost": 146.53,
      "subscription": "sub-idf-01",
      "name": "rg-nassim-laidi"
    },
    {
      "cost": 94.8,
      "subscription": "sub-idf-01",
      "name": "rg-sylvain-pages"
    },
    {
      "cost": 85.92,
      "subscription": "sub-idf-01",
      "name": "rg-imade-bouziane"
    }
  ],
  "totalPrevious": 4595.37,
  "lastUpdated": "2026-04-23 07:57",
  "delta": -44.1,
  "totalMTD": 2568.85,
  "subscriptions": [
    {
      "previous": 3627.0,
      "mtd": 2323.65,
      "name": "sub-idf-01"
    },
    {
      "previous": 2.76,
      "mtd": 0.0,
      "name": "sub-lille-01"
    },
    {
      "previous": 901.22,
      "mtd": 216.15,
      "name": "sub-lyon-01"
    },
    {
      "previous": 0,
      "mtd": 0,
      "name": "sub-marseille-01"
    },
    {
      "previous": 64.39,
      "mtd": 29.05,
      "name": "sub-nantes-01"
    },
    {
      "previous": 0.0,
      "mtd": 0,
      "name": "sub-temp-01"
    }
  ]
}
